{"__all__":[{"d":"2026-07-17","t":10286,"health":195,"account":408,"report":177,"payment":41,"communication":308,"usage_studio":406,"feature_adoption":4683,"image_pendency":42,"pendency_360":3553,"usage_vini":142,"signals":201,"tickets":130},{"d":"2026-07-18","t":7968,"health":184,"account":408,"report":177,"payment":41,"communication":308,"usage_studio":410,"feature_adoption":4708,"image_pendency":7,"pendency_360":1242,"usage_vini":140,"signals":202,"tickets":141},{"d":"2026-07-19","t":10256,"health":233,"account":408,"report":178,"payment":41,"communication":293,"usage_studio":410,"feature_adoption":4711,"image_pendency":36,"pendency_360":3485,"usage_vini":140,"signals":203,"tickets":118},{"d":"2026-07-20","t":10195,"health":252,"account":407,"report":178,"payment":41,"communication":293,"usage_studio":410,"feature_adoption":4685,"image_pendency":41,"pendency_360":3454,"usage_vini":141,"signals":170,"tickets":123},{"d":"2026-07-21","t":10534,"health":217,"account":408,"report":169,"payment":40,"communication":295,"usage_studio":460,"feature_adoption":4825,"image_pendency":37,"pendency_360":3616,"usage_vini":145,"signals":177,"tickets":145},{"d":"2026-07-22","t":10360,"health":187,"account":408,"report":160,"payment":49,"communication":295,"usage_studio":412,"feature_adoption":4797,"image_pendency":44,"pendency_360":3585,"usage_vini":87,"signals":176,"tickets":160}],"Abhijeet Mitra":[{"d":"2026-07-17","t":966,"health":17,"account":38,"report":10,"payment":6,"communication":12,"usage_studio":43,"feature_adoption":464,"image_pendency":23,"pendency_360":332,"usage_vini":11,"signals":4,"tickets":6},{"d":"2026-07-18","t":721,"health":16,"account":38,"report":10,"payment":6,"communication":12,"usage_studio":43,"feature_adoption":464,"image_pendency":7,"pendency_360":104,"usage_vini":11,"signals":4,"tickets":6},{"d":"2026-07-19","t":948,"health":16,"account":38,"report":10,"payment":6,"communication":11,"usage_studio":43,"feature_adoption":465,"image_pendency":16,"pendency_360":325,"usage_vini":11,"signals":4,"tickets":3},{"d":"2026-07-20","t":964,"health":29,"account":38,"report":10,"payment":6,"communication":11,"usage_studio":43,"feature_adoption":463,"image_pendency":20,"pendency_360":324,"usage_vini":11,"signals":4,"tickets":5},{"d":"2026-07-21","t":934,"health":9,"account":38,"report":5,"payment":4,"communication":11,"usage_studio":43,"feature_adoption":463,"image_pendency":17,"pendency_360":319,"usage_vini":11,"signals":3,"tickets":11},{"d":"2026-07-22","t":939,"health":13,"account":38,"report":5,"payment":8,"communication":11,"usage_studio":43,"feature_adoption":453,"image_pendency":16,"pendency_360":327,"usage_vini":8,"signals":4,"tickets":13}],"Aditya Kaul":[{"d":"2026-07-17","t":364,"health":15,"account":49,"report":12,"payment":3,"communication":9,"usage_studio":15,"feature_adoption":173,"image_pendency":2,"pendency_360":55,"usage_vini":15,"signals":6,"tickets":10},{"d":"2026-07-18","t":339,"health":15,"account":49,"report":12,"payment":3,"communication":9,"usage_studio":15,"feature_adoption":173,"image_pendency":0,"pendency_360":31,"usage_vini":15,"signals":6,"tickets":11},{"d":"2026-07-19","t":367,"health":15,"account":49,"report":12,"payment":3,"communication":9,"usage_studio":15,"feature_adoption":173,"image_pendency":2,"pendency_360":57,"usage_vini":15,"signals":6,"tickets":11},{"d":"2026-07-20","t":364,"health":15,"account":49,"report":12,"payment":3,"communication":9,"usage_studio":15,"feature_adoption":172,"image_pendency":2,"pendency_360":57,"usage_vini":15,"signals":6,"tickets":9},{"d":"2026-07-21","t":377,"health":17,"account":49,"report":11,"payment":3,"communication":10,"usage_studio":16,"feature_adoption":179,"image_pendency":2,"pendency_360":59,"usage_vini":15,"signals":6,"tickets":10},{"d":"2026-07-22","t":352,"health":13,"account":49,"report":11,"payment":2,"communication":11,"usage_studio":13,"feature_adoption":179,"image_pendency":2,"pendency_360":41,"usage_vini":14,"signals":4,"tickets":13}],"Akash Jaiswal":[{"d":"2026-07-17","t":183,"health":0,"account":14,"report":14,"payment":0,"communication":6,"usage_studio":20,"feature_adoption":103,"image_pendency":0,"pendency_360":0,"usage_vini":0,"signals":25,"tickets":1},{"d":"2026-07-18","t":183,"health":0,"account":14,"report":14,"payment":0,"communication":6,"usage_studio":20,"feature_adoption":103,"image_pendency":0,"pendency_360":0,"usage_vini":0,"signals":25,"tickets":1},{"d":"2026-07-19","t":183,"health":0,"account":14,"report":14,"payment":0,"communication":6,"usage_studio":20,"feature_adoption":103,"image_pendency":0,"pendency_360":0,"usage_vini":0,"signals":25,"tickets":1},{"d":"2026-07-20","t":160,"health":0,"account":14,"report":14,"payment":0,"communication":6,"usage_studio":20,"feature_adoption":104,"image_pendency":0,"pendency_360":0,"usage_vini":0,"signals":1,"tickets":1},{"d":"2026-07-21","t":160,"health":0,"account":14,"report":14,"payment":0,"communication":6,"usage_studio":20,"feature_adoption":104,"image_pendency":0,"pendency_360":0,"usage_vini":0,"signals":1,"tickets":1},{"d":"2026-07-22","t":169,"health":0,"account":14,"report":14,"payment":1,"communication":6,"usage_studio":20,"feature_adoption":104,"image_pendency":0,"pendency_360":0,"usage_vini":0,"signals":8,"tickets":2}],"Aman Seth":[{"d":"2026-07-17","t":626,"health":4,"account":1,"report":9,"payment":0,"communication":1,"usage_studio":43,"feature_adoption":550,"image_pendency":1,"pendency_360":13,"usage_vini":0,"signals":3,"tickets":1},{"d":"2026-07-18","t":618,"health":4,"account":1,"report":9,"payment":0,"communication":1,"usage_studio":43,"feature_adoption":554,"image_pendency":0,"pendency_360":2,"usage_vini":0,"signals":3,"tickets":1},{"d":"2026-07-19","t":660,"health":34,"account":1,"report":9,"payment":0,"communication":1,"usage_studio":43,"feature_adoption":554,"image_pendency":1,"pendency_360":13,"usage_vini":0,"signals":3,"tickets":1},{"d":"2026-07-20","t":654,"health":34,"account":1,"report":9,"payment":0,"communication":1,"usage_studio":42,"feature_adoption":547,"image_pendency":1,"pendency_360":13,"usage_vini":0,"signals":2,"tickets":4},{"d":"2026-07-21","t":635,"health":4,"account":3,"report":10,"payment":0,"communication":1,"usage_studio":44,"feature_adoption":555,"image_pendency":1,"pendency_360":13,"usage_vini":0,"signals":2,"tickets":2},{"d":"2026-07-22","t":636,"health":4,"account":3,"report":10,"payment":0,"communication":1,"usage_studio":44,"feature_adoption":556,"image_pendency":1,"pendency_360":13,"usage_vini":0,"signals":2,"tickets":2}],"Ankur Batra":[{"d":"2026-07-17","t":893,"health":36,"account":63,"report":17,"payment":7,"communication":0,"usage_studio":28,"feature_adoption":235,"image_pendency":0,"pendency_360":444,"usage_vini":38,"signals":9,"tickets":16},{"d":"2026-07-18","t":586,"health":35,"account":63,"report":17,"payment":7,"communication":0,"usage_studio":28,"feature_adoption":236,"image_pendency":0,"pendency_360":141,"usage_vini":36,"signals":9,"tickets":14},{"d":"2026-07-19","t":891,"health":45,"account":63,"report":17,"payment":7,"communication":0,"usage_studio":28,"feature_adoption":236,"image_pendency":0,"pendency_360":440,"usage_vini":37,"signals":9,"tickets":9},{"d":"2026-07-20","t":883,"health":47,"account":63,"report":17,"payment":7,"communication":0,"usage_studio":28,"feature_adoption":237,"image_pendency":0,"pendency_360":430,"usage_vini":38,"signals":6,"tickets":10},{"d":"2026-07-21","t":884,"health":38,"account":63,"report":8,"payment":7,"communication":0,"usage_studio":32,"feature_adoption":245,"image_pendency":0,"pendency_360":429,"usage_vini":40,"signals":6,"tickets":16},{"d":"2026-07-22","t":846,"health":48,"account":63,"report":5,"payment":4,"communication":0,"usage_studio":16,"feature_adoption":244,"image_pendency":0,"pendency_360":421,"usage_vini":21,"signals":6,"tickets":18}],"Anuj Tewatia":[{"d":"2026-07-17","t":901,"health":10,"account":10,"report":20,"payment":3,"communication":102,"usage_studio":66,"feature_adoption":675,"image_pendency":5,"pendency_360":0,"usage_vini":0,"signals":9,"tickets":1},{"d":"2026-07-18","t":896,"health":10,"account":10,"report":20,"payment":3,"communication":102,"usage_studio":66,"feature_adoption":675,"image_pendency":0,"pendency_360":0,"usage_vini":0,"signals":9,"tickets":1},{"d":"2026-07-19","t":900,"health":10,"account":10,"report":20,"payment":3,"communication":98,"usage_studio":66,"feature_adoption":676,"image_pendency":6,"pendency_360":0,"usage_vini":0,"signals":10,"tickets":1},{"d":"2026-07-20","t":897,"health":10,"account":10,"report":20,"payment":3,"communication":98,"usage_studio":67,"feature_adoption":673,"image_pendency":6,"pendency_360":0,"usage_vini":0,"signals":10,"tickets":0},{"d":"2026-07-21","t":918,"health":13,"account":10,"report":22,"payment":4,"communication":99,"usage_studio":69,"feature_adoption":684,"image_pendency":6,"pendency_360":0,"usage_vini":0,"signals":11,"tickets":0},{"d":"2026-07-22","t":922,"health":13,"account":10,"report":23,"payment":8,"communication":99,"usage_studio":69,"feature_adoption":682,"image_pendency":6,"pendency_360":0,"usage_vini":0,"signals":12,"tickets":0}],"Jaspreet Kaur":[{"d":"2026-07-17","t":678,"health":36,"account":30,"report":12,"payment":5,"communication":5,"usage_studio":21,"feature_adoption":302,"image_pendency":1,"pendency_360":211,"usage_vini":23,"signals":5,"tickets":27},{"d":"2026-07-18","t":582,"health":36,"account":30,"report":12,"payment":5,"communication":5,"usage_studio":21,"feature_adoption":302,"image_pendency":0,"pendency_360":108,"usage_vini":23,"signals":5,"tickets":35},{"d":"2026-07-19","t":678,"health":37,"account":30,"report":12,"payment":5,"communication":5,"usage_studio":21,"feature_adoption":302,"image_pendency":1,"pendency_360":205,"usage_vini":22,"signals":5,"tickets":33},{"d":"2026-07-20","t":664,"health":37,"account":30,"report":12,"payment":5,"communication":5,"usage_studio":21,"feature_adoption":302,"image_pendency":3,"pendency_360":192,"usage_vini":22,"signals":5,"tickets":30},{"d":"2026-07-21","t":698,"health":47,"account":30,"report":8,"payment":5,"communication":5,"usage_studio":27,"feature_adoption":319,"image_pendency":3,"pendency_360":192,"usage_vini":23,"signals":5,"tickets":34},{"d":"2026-07-22","t":651,"health":32,"account":30,"report":6,"payment":3,"communication":4,"usage_studio":15,"feature_adoption":315,"image_pendency":3,"pendency_360":183,"usage_vini":16,"signals":5,"tickets":39}],"Madhav Uppal":[{"d":"2026-07-22","t":5,"health":0,"account":3,"report":1,"payment":0,"communication":0,"usage_studio":0,"feature_adoption":0,"image_pendency":0,"pendency_360":0,"usage_vini":1,"signals":0,"tickets":0}],"Manpreet Kaur":[{"d":"2026-07-17","t":558,"health":4,"account":15,"report":6,"payment":5,"communication":56,"usage_studio":24,"feature_adoption":335,"image_pendency":6,"pendency_360":92,"usage_vini":0,"signals":14,"tickets":1},{"d":"2026-07-18","t":499,"health":4,"account":15,"report":6,"payment":5,"communication":56,"usage_studio":24,"feature_adoption":338,"image_pendency":0,"pendency_360":35,"usage_vini":0,"signals":14,"tickets":2},{"d":"2026-07-19","t":555,"health":4,"account":15,"report":6,"payment":5,"communication":52,"usage_studio":24,"feature_adoption":338,"image_pendency":6,"pendency_360":89,"usage_vini":0,"signals":14,"tickets":2},{"d":"2026-07-20","t":540,"health":4,"account":15,"report":6,"payment":5,"communication":52,"usage_studio":24,"feature_adoption":332,"image_pendency":6,"pendency_360":79,"usage_vini":0,"signals":14,"tickets":3},{"d":"2026-07-21","t":558,"health":4,"account":14,"report":6,"payment":5,"communication":52,"usage_studio":24,"feature_adoption":342,"image_pendency":6,"pendency_360":88,"usage_vini":0,"signals":14,"tickets":3},{"d":"2026-07-22","t":551,"health":3,"account":14,"report":6,"payment":6,"communication":52,"usage_studio":24,"feature_adoption":338,"image_pendency":7,"pendency_360":84,"usage_vini":0,"signals":14,"tickets":3}],"Prabha Kumari":[{"d":"2026-07-17","t":659,"health":33,"account":74,"report":12,"payment":3,"communication":1,"usage_studio":20,"feature_adoption":429,"image_pendency":2,"pendency_360":44,"usage_vini":12,"signals":0,"tickets":29},{"d":"2026-07-18","t":636,"health":23,"account":74,"report":12,"payment":3,"communication":1,"usage_studio":24,"feature_adoption":444,"image_pendency":0,"pendency_360":15,"usage_vini":12,"signals":0,"tickets":28},{"d":"2026-07-19","t":677,"health":32,"account":74,"report":12,"payment":3,"communication":0,"usage_studio":24,"feature_adoption":444,"image_pendency":3,"pendency_360":52,"usage_vini":12,"signals":0,"tickets":21},{"d":"2026-07-20","t":672,"health":33,"account":73,"report":12,"payment":3,"communication":0,"usage_studio":24,"feature_adoption":439,"image_pendency":3,"pendency_360":53,"usage_vini":12,"signals":0,"tickets":20},{"d":"2026-07-21","t":712,"health":37,"account":73,"report":11,"payment":5,"communication":0,"usage_studio":36,"feature_adoption":455,"image_pendency":2,"pendency_360":52,"usage_vini":13,"signals":1,"tickets":27},{"d":"2026-07-22","t":685,"health":30,"account":70,"report":9,"payment":4,"communication":0,"usage_studio":27,"feature_adoption":453,"image_pendency":1,"pendency_360":53,"usage_vini":9,"signals":1,"tickets":28}],"Prathamesh Prashant":[{"d":"2026-07-17","t":266,"health":3,"account":5,"report":3,"payment":2,"communication":29,"usage_studio":14,"feature_adoption":175,"image_pendency":0,"pendency_360":35,"usage_vini":0,"signals":0,"tickets":0},{"d":"2026-07-18","t":236,"health":3,"account":5,"report":3,"payment":2,"communication":29,"usage_studio":14,"feature_adoption":175,"image_pendency":0,"pendency_360":5,"usage_vini":0,"signals":0,"tickets":0},{"d":"2026-07-19","t":267,"health":3,"account":5,"report":4,"payment":2,"communication":29,"usage_studio":14,"feature_adoption":175,"image_pendency":0,"pendency_360":35,"usage_vini":0,"signals":0,"tickets":0},{"d":"2026-07-20","t":267,"health":3,"account":5,"report":4,"payment":2,"communication":29,"usage_studio":14,"feature_adoption":175,"image_pendency":0,"pendency_360":35,"usage_vini":0,"signals":0,"tickets":0},{"d":"2026-07-21","t":262,"health":3,"account":5,"report":4,"payment":2,"communication":24,"usage_studio":14,"feature_adoption":175,"image_pendency":0,"pendency_360":35,"usage_vini":0,"signals":0,"tickets":0},{"d":"2026-07-22","t":266,"health":3,"account":5,"report":4,"payment":4,"communication":24,"usage_studio":14,"feature_adoption":175,"image_pendency":0,"pendency_360":33,"usage_vini":0,"signals":0,"tickets":4}],"Ritika Agarwal":[{"d":"2026-07-17","t":795,"health":3,"account":19,"report":9,"payment":0,"communication":7,"usage_studio":13,"feature_adoption":158,"image_pendency":0,"pendency_360":561,"usage_vini":11,"signals":10,"tickets":4},{"d":"2026-07-18","t":544,"health":3,"account":19,"report":9,"payment":0,"communication":7,"usage_studio":13,"feature_adoption":158,"image_pendency":0,"pendency_360":311,"usage_vini":11,"signals":8,"tickets":5},{"d":"2026-07-19","t":788,"health":3,"account":19,"report":9,"payment":0,"communication":7,"usage_studio":13,"feature_adoption":158,"image_pendency":0,"pendency_360":556,"usage_vini":11,"signals":8,"tickets":4},{"d":"2026-07-20","t":782,"health":4,"account":19,"report":9,"payment":0,"communication":7,"usage_studio":13,"feature_adoption":158,"image_pendency":0,"pendency_360":548,"usage_vini":11,"signals":7,"tickets":6},{"d":"2026-07-21","t":826,"health":4,"account":19,"report":10,"payment":0,"communication":7,"usage_studio":18,"feature_adoption":174,"image_pendency":0,"pendency_360":566,"usage_vini":12,"signals":9,"tickets":7},{"d":"2026-07-22","t":825,"health":4,"account":19,"report":9,"payment":0,"communication":7,"usage_studio":14,"feature_adoption":174,"image_pendency":7,"pendency_360":565,"usage_vini":8,"signals":10,"tickets":8}],"Sanyam Tyagi":[{"d":"2026-07-17","t":402,"health":4,"account":22,"report":5,"payment":0,"communication":22,"usage_studio":12,"feature_adoption":214,"image_pendency":1,"pendency_360":81,"usage_vini":2,"signals":36,"tickets":3},{"d":"2026-07-18","t":336,"health":4,"account":22,"report":5,"payment":0,"communication":22,"usage_studio":12,"feature_adoption":215,"image_pendency":0,"pendency_360":12,"usage_vini":2,"signals":36,"tickets":6},{"d":"2026-07-19","t":409,"health":4,"account":22,"report":5,"payment":0,"communication":21,"usage_studio":12,"feature_adoption":215,"image_pendency":1,"pendency_360":85,"usage_vini":2,"signals":36,"tickets":6},{"d":"2026-07-20","t":414,"health":4,"account":22,"report":5,"payment":0,"communication":21,"usage_studio":12,"feature_adoption":216,"image_pendency":0,"pendency_360":86,"usage_vini":2,"signals":36,"tickets":10},{"d":"2026-07-21","t":541,"health":2,"account":22,"report":6,"payment":0,"communication":22,"usage_studio":13,"feature_adoption":219,"image_pendency":0,"pendency_360":209,"usage_vini":2,"signals":38,"tickets":8},{"d":"2026-07-22","t":528,"health":4,"account":22,"report":5,"payment":0,"communication":21,"usage_studio":12,"feature_adoption":215,"image_pendency":0,"pendency_360":201,"usage_vini":2,"signals":38,"tickets":8}],"Vedant Choudhary":[{"d":"2026-07-17","t":435,"health":1,"account":8,"report":15,"payment":0,"communication":9,"usage_studio":48,"feature_adoption":289,"image_pendency":0,"pendency_360":33,"usage_vini":0,"signals":27,"tickets":5},{"d":"2026-07-18","t":416,"health":1,"account":8,"report":15,"payment":0,"communication":9,"usage_studio":48,"feature_adoption":289,"image_pendency":0,"pendency_360":14,"usage_vini":0,"signals":28,"tickets":4},{"d":"2026-07-19","t":431,"health":0,"account":8,"report":15,"payment":0,"communication":9,"usage_studio":48,"feature_adoption":289,"image_pendency":0,"pendency_360":31,"usage_vini":0,"signals":28,"tickets":3},{"d":"2026-07-20","t":434,"health":1,"account":8,"report":16,"payment":0,"communication":9,"usage_studio":48,"feature_adoption":289,"image_pendency":0,"pendency_360":31,"usage_vini":1,"signals":27,"tickets":4},{"d":"2026-07-21","t":436,"health":0,"account":8,"report":17,"payment":0,"communication":9,"usage_studio":49,"feature_adoption":293,"image_pendency":0,"pendency_360":31,"usage_vini":1,"signals":27,"tickets":1},{"d":"2026-07-22","t":422,"health":0,"account":8,"report":16,"payment":0,"communication":9,"usage_studio":49,"feature_adoption":293,"image_pendency":0,"pendency_360":28,"usage_vini":0,"signals":18,"tickets":1}],"Vishal Singh1":[{"d":"2026-07-17","t":411,"health":10,"account":9,"report":8,"payment":5,"communication":27,"usage_studio":16,"feature_adoption":213,"image_pendency":1,"pendency_360":107,"usage_vini":7,"signals":0,"tickets":8},{"d":"2026-07-18","t":349,"health":10,"account":9,"report":8,"payment":5,"communication":27,"usage_studio":16,"feature_adoption":213,"image_pendency":0,"pendency_360":46,"usage_vini":7,"signals":0,"tickets":8},{"d":"2026-07-19","t":400,"health":10,"account":9,"report":8,"payment":5,"communication":25,"usage_studio":16,"feature_adoption":213,"image_pendency":0,"pendency_360":99,"usage_vini":7,"signals":0,"tickets":8},{"d":"2026-07-20","t":391,"health":10,"account":9,"report":8,"payment":5,"communication":25,"usage_studio":16,"feature_adoption":212,"image_pendency":0,"pendency_360":91,"usage_vini":7,"signals":0,"tickets":8},{"d":"2026-07-21","t":407,"health":13,"account":9,"report":9,"payment":5,"communication":26,"usage_studio":19,"feature_adoption":212,"image_pendency":0,"pendency_360":99,"usage_vini":7,"signals":0,"tickets":8},{"d":"2026-07-22","t":385,"health":8,"account":9,"report":8,"payment":8,"communication":26,"usage_studio":16,"feature_adoption":209,"image_pendency":1,"pendency_360":90,"usage_vini":5,"signals":0,"tickets":5}],"Zeeshana Aijaz":[{"d":"2026-07-17","t":1758,"health":13,"account":19,"report":3,"payment":2,"communication":6,"usage_studio":20,"feature_adoption":326,"image_pendency":0,"pendency_360":1348,"usage_vini":4,"signals":2,"tickets":15},{"d":"2026-07-18","t":796,"health":13,"account":19,"report":3,"payment":2,"communication":6,"usage_studio":20,"feature_adoption":327,"image_pendency":0,"pendency_360":383,"usage_vini":4,"signals":3,"tickets":16},{"d":"2026-07-19","t":1718,"health":13,"account":19,"report":3,"payment":2,"communication":4,"usage_studio":20,"feature_adoption":327,"image_pendency":0,"pendency_360":1311,"usage_vini":4,"signals":3,"tickets":12},{"d":"2026-07-20","t":1727,"health":12,"account":19,"report":3,"payment":2,"communication":4,"usage_studio":20,"feature_adoption":323,"image_pendency":0,"pendency_360":1328,"usage_vini":4,"signals":2,"tickets":10},{"d":"2026-07-21","t":1739,"health":11,"account":19,"report":3,"payment":0,"communication":3,"usage_studio":20,"feature_adoption":326,"image_pendency":0,"pendency_360":1338,"usage_vini":4,"signals":3,"tickets":12},{"d":"2026-07-22","t":1785,"health":7,"account":19,"report":3,"payment":0,"communication":4,"usage_studio":19,"feature_adoption":327,"image_pendency":0,"pendency_360":1391,"usage_vini":2,"signals":2,"tickets":11}]}